multiagent_auction/__init__.py
multiagent_auction/agent.py
multiagent_auction/argparser.py
multiagent_auction/buffer.py
multiagent_auction/clear.py
multiagent_auction/env.py
multiagent_auction/evaluation.py
multiagent_auction/experiment.py
multiagent_auction/maddpg.py
multiagent_auction/networks.py
multiagent_auction/run.py
multiagent_auction/train.py
multiagent_auction/utils.py
multiagent_auction-0.1.1.dist-info/licenses/LICENSE
multiagent_auction-0.1.1.dist-info/METADATA
multiagent_auction-0.1.1.dist-info/WHEEL
multiagent_auction-0.1.1.dist-info/entry_points.txt
multiagent_auction-0.1.1.dist-info/top_level.txt
multiagent_auction-0.1.1.dist-info/RECORD
