Metadata-Version: 2.4
Name: multiagent_auction
Version: 0.1.1
Summary: Multi-agent auction simulations using DRL
Maintainer-email: Luis Eduardo Craizer <lecraizer@gmail.com>, Fernanda Gomes <fernandalsgomes06@gmail.com>, Moacyr Silva Alvim <moacyr.alvim@gmail.com>
License: MIT
Project-URL: Homepage, https://github.com/lecraizer/multiagent_auction
Project-URL: Issues, https://github.com/lecraizer/multiagent_auction/issues
Classifier: Programming Language :: Python :: 3
Classifier: License :: OSI Approved :: MIT License
Classifier: Operating System :: OS Independent
Requires-Python: >=3.7
License-File: LICENSE
Requires-Dist: numpy
Requires-Dist: torch
Requires-Dist: matplotlib
Requires-Dist: gym
Requires-Dist: playsound
Dynamic: license-file
